siyi_sdk/.git
siyi_sdk/LICENSE
siyi_sdk/README.md
siyi_sdk/__init__.py
siyi_sdk/cameras.py
siyi_sdk/crc16_python.py
siyi_sdk/gui/demo.mp4
siyi_sdk/gui/gui_tkinter.png
siyi_sdk/gui/tkgui.py
siyi_sdk/siyi_message.py
siyi_sdk/siyi_sdk.bak.py
siyi_sdk/siyi_sdk.py
siyi_sdk/src/rtsp_gstreamer.cpp
siyi_sdk/stream.py
siyi_sdk/tests/__init__.py
siyi_sdk/tests/test_absolute_zoom.py
siyi_sdk/tests/test_center_gimbal.py
siyi_sdk/tests/test_follow_mode.py
siyi_sdk/tests/test_fpv_mode.py
siyi_sdk/tests/test_from_rtsp_to_rtmp.py
siyi_sdk/tests/test_get_fw_ver.py
siyi_sdk/tests/test_get_gimbal_info.py
siyi_sdk/tests/test_get_hw_id.py
siyi_sdk/tests/test_gimbal_rotation.py
siyi_sdk/tests/test_lock_mode.py
siyi_sdk/tests/test_print_attitude.py
siyi_sdk/tests/test_record_video.py
siyi_sdk/tests/test_rtmp_stream.py
siyi_sdk/tests/test_rtsp.py
siyi_sdk/tests/test_set_angles.py
siyi_sdk/tests/test_zoom.py
siyi_sdk/tests/udp_server.py
siyi_sdk/utils.py
siyi_sdk-0.2.11.dist-info/METADATA
siyi_sdk-0.2.11.dist-info/WHEEL
siyi_sdk-0.2.11.dist-info/RECORD
